jupyterlab_code_formatter/__init__.py
jupyterlab_code_formatter/_version.py
jupyterlab_code_formatter/formatters.py
jupyterlab_code_formatter/handlers.py
jupyterlab_code_formatter/tests/__init__.py
jupyterlab_code_formatter/tests/conftest.py
jupyterlab_code_formatter/tests/test_formatters.py
jupyterlab_code_formatter/tests/test_handlers.py
jupyterlab_code_formatter-3.0.2.data/data/etc/jupyter/jupyter_notebook_config.d/jupyterlab_code_formatter.json
jupyterlab_code_formatter-3.0.2.data/data/etc/jupyter/jupyter_server_config.d/jupyterlab_code_formatter.json
jupyterlab_code_formatter-3.0.2.data/data/share/jupyter/labextensions/jupyterlab_code_formatter/package.json
jupyterlab_code_formatter-3.0.2.data/data/share/jupyter/labextensions/jupyterlab_code_formatter/schemas/jupyterlab_code_formatter/package.json.orig
jupyterlab_code_formatter-3.0.2.data/data/share/jupyter/labextensions/jupyterlab_code_formatter/schemas/jupyterlab_code_formatter/settings.json
jupyterlab_code_formatter-3.0.2.data/data/share/jupyter/labextensions/jupyterlab_code_formatter/static/728.db7f0f2fef10b09079c3.js
jupyterlab_code_formatter-3.0.2.data/data/share/jupyter/labextensions/jupyterlab_code_formatter/static/98.b4d9a08e3fbed2dba126.js
jupyterlab_code_formatter-3.0.2.data/data/share/jupyter/labextensions/jupyterlab_code_formatter/static/remoteEntry.cb0ad1eca63be149c14b.js
jupyterlab_code_formatter-3.0.2.data/data/share/jupyter/labextensions/jupyterlab_code_formatter/static/style.js
jupyterlab_code_formatter-3.0.2.data/data/share/jupyter/labextensions/jupyterlab_code_formatter/static/third-party-licenses.json
jupyterlab_code_formatter-3.0.2.data/data/share/jupyter/labextensions/jupyterlab_code_formatter/install.json
jupyterlab_code_formatter-3.0.2.dist-info/METADATA
jupyterlab_code_formatter-3.0.2.dist-info/WHEEL
jupyterlab_code_formatter-3.0.2.dist-info/licenses/LICENSE
jupyterlab_code_formatter-3.0.2.dist-info/RECORD
