Metadata-Version: 2.3
Name: jupyterlab_code_formatter
Version: 3.0.2
Dynamic: Keywords
Summary:  A JupyterLab plugin to facilitate invocation of code formatters.
Project-URL: Homepage,  https://github.com/jupyterlab-contrib/jupyterlab_code_formatter
Project-URL: Bug Tracker,  https://github.com/jupyterlab-contrib/jupyterlab_code_formatter/issues
Project-URL: Repository,  https://github.com/jupyterlab-contrib/jupyterlab_code_formatter.git
Author-email: Ryan Tam <ryantam626@gmail.com>
License: Copyright 2023 Ryan TAM
License-File: LICENSE
Classifier: Framework :: Jupyter
Classifier: Framework :: Jupyter :: JupyterLab
Classifier: Framework :: Jupyter :: JupyterLab :: 4
Classifier: Framework :: Jupyter :: JupyterLab :: Extensions
Classifier: Framework :: Jupyter :: JupyterLab :: Extensions :: Prebuilt
Classifier: License :: OSI Approved :: BSD License
Classifier: Programming Language :: Python
Classifier: Programming Language :: Python :: 3
Classifier: Programming Language :: Python :: 3.7
Classifier: Programming Language :: Python :: 3.8
Classifier: Programming Language :: Python :: 3.9
Classifier: Programming Language :: Python :: 3.10
Classifier: Programming Language :: Python :: 3.11
Requires-Python: >=3.7
Requires-Dist: jupyter-server<3,>=1.21
Requires-Dist: packaging
Provides-Extra: dev
Requires-Dist: autopep8; extra == 'dev'
Requires-Dist: black==22.1.0; extra == 'dev'
Requires-Dist: blue==0.9.1; extra == 'dev'
Requires-Dist: click==8.0.2; extra == 'dev'
Requires-Dist: isort; extra == 'dev'
Requires-Dist: jupyterlab>=3.0.0; extra == 'dev'
Requires-Dist: rpy2; extra == 'dev'
Requires-Dist: ruff; extra == 'dev'
Requires-Dist: yapf; extra == 'dev'
Provides-Extra: test
Requires-Dist: black==22.1.0; extra == 'test'
Requires-Dist: blue==0.9.1; extra == 'test'
Requires-Dist: coverage; extra == 'test'
Requires-Dist: importlib-metadata; (python_version < '3.8') and extra == 'test'
Requires-Dist: isort; extra == 'test'
Requires-Dist: pytest; extra == 'test'
Requires-Dist: pytest-asyncio; extra == 'test'
Requires-Dist: pytest-cov; extra == 'test'
Requires-Dist: pytest-jupyter[server]>=0.6.0; extra == 'test'
Requires-Dist: rpy2; extra == 'test'
Requires-Dist: ruff; extra == 'test'
Requires-Dist: yapf; extra == 'test'
